mychevy/__init__.py
mychevy/cli.py
mychevy/debug.py
mychevy/mychevy.py
mychevy-1.2.0.dist-info/AUTHORS.rst
mychevy-1.2.0.dist-info/LICENSE
mychevy-1.2.0.dist-info/METADATA
mychevy-1.2.0.dist-info/WHEEL
mychevy-1.2.0.dist-info/entry_points.txt
mychevy-1.2.0.dist-info/top_level.txt
mychevy-1.2.0.dist-info/RECORD
