Metadata-Version: 2.1
Name: mychevy
Version: 1.2.0
Summary: Python interface to My Chevy online data
Home-page: https://github.com/sdague/mychevy
Author: Sean Dague
Author-email: sean@dague.net
License: Apache Software License 2.0
Keywords: mychevy
Platform: UNKNOWN
Classifier: Development Status :: 2 - Pre-Alpha
Classifier: Intended Audience :: Developers
Classifier: License :: OSI Approved :: Apache Software License
Classifier: Natural Language :: English
Classifier: Programming Language :: Python :: 3
Classifier: Programming Language :: Python :: 3.5
Classifier: Programming Language :: Python :: 3.6
Requires-Dist: requests
Requires-Dist: click (>=6)
